is_the_build_done_yet/__init__.py
is_the_build_done_yet/is_the_build_done_yet.py
is_the_build_done_yet-1.0.0.dist-info/LICENSE
is_the_build_done_yet-1.0.0.dist-info/METADATA
is_the_build_done_yet-1.0.0.dist-info/WHEEL
is_the_build_done_yet-1.0.0.dist-info/entry_points.txt
is_the_build_done_yet-1.0.0.dist-info/top_level.txt
is_the_build_done_yet-1.0.0.dist-info/RECORD
