Metadata-Version: 2.1
Name: is-the-build-done-yet
Version: 1.0.0
Summary: Make Hue lights change colour when a subprocess is complete
Home-page: https://github.com/JosiahCraw/Is-the-Build-Done-Yet
Author: Josiah Craw
Author-email: jos@joscraw.net
License: UNKNOWN
Platform: UNKNOWN
Classifier: Programming Language :: Python :: 3
Classifier: License :: OSI Approved :: MIT License
Classifier: Operating System :: OS Independent
Requires-Python: >=3.6
